cuvis/AcquisitionContext.py
cuvis/Async.py
cuvis/Calibration.py
cuvis/Export.py
cuvis/FileWriteSettings.py
cuvis/General.py
cuvis/Measurement.py
cuvis/ProcessingContext.py
cuvis/SessionFile.py
cuvis/Viewer.py
cuvis/Worker.py
cuvis/__init__.py
cuvis/_cuvis_il.py
cuvis/cube_utils.py
cuvis/cuvis_aux.py
cuvis/cuvis_types.py
cuvis/doc.py
cuvis-3.5.0.1.dist-info/licenses/LICENSE
cuvis-3.5.0.1.dist-info/METADATA
cuvis-3.5.0.1.dist-info/WHEEL
cuvis-3.5.0.1.dist-info/top_level.txt
cuvis-3.5.0.1.dist-info/RECORD
