Metadata-Version: 2.4
Name: cuvis
Version: 3.5.0.1
Summary: CUVIS Python SDK.
Author-email: "Cubert GmbH, Ulm, Germany" <sdk@cubert-gmbh.com>
License-Expression: Apache-2.0
Project-URL: Homepage, https://www.cubert-hyperspectral.com/
Project-URL: Repository, https://github.com/cubert-hyperspectral/cuvis.python
Project-URL: Documentation, https://cubert-hyperspectral.github.io/cuvis.doc/
Project-URL: Changelog, https://github.com/cubert-hyperspectral/cuvis.python/releases
Project-URL: Issues, https://github.com/cubert-hyperspectral/cuvis.python/issues
Classifier: Intended Audience :: Developers
Classifier: Programming Language :: Python :: 3
Classifier: Programming Language :: Python :: 3.9
Classifier: Programming Language :: Python :: 3.10
Classifier: Programming Language :: Python :: 3.11
Classifier: Programming Language :: Python :: 3.12
Classifier: Programming Language :: Python :: 3.13
Classifier: Programming Language :: Python :: 3.14
Classifier: Topic :: Scientific/Engineering :: Image Processing
Requires-Python: >=3.9
License-File: LICENSE
Requires-Dist: cuvis-il<3.6.0,>=3.5.0
Requires-Dist: typing_extensions; python_version < "3.10"
Requires-Dist: setuptools; python_version >= "3.12"
Dynamic: license-file
